CHANGES.txt
LICENSE.txt
MANIFEST.in
README.txt
setup.py
hindsight/__init__.py
hindsight/behave.py
hindsight/cli.py
hindsight.egg-info/PKG-INFO
hindsight.egg-info/SOURCES.txt
hindsight.egg-info/dependency_links.txt
hindsight.egg-info/entry_points.txt
hindsight.egg-info/top_level.txt