Metadata-Version: 1.1
Name: hindsight
Version: 0.1.4
Summary: Python tools for Hindsight Software
Home-page: http://pypi.python.org/pypi/hindsight/
Author: Jack Bastow
Author-email: jack.bastow@hindsightsoftware.co.uk
License: Creative Commons Attribution-Noncommercial-Share Alike license
Platform: UNKNOWN
Classifier: Programming Language :: Python :: 2
Classifier: Programming Language :: Python :: 3
Classifier: Topic :: Software Development
